dotenvmodel/__init__.py
dotenvmodel/coercion.py
dotenvmodel/config.py
dotenvmodel/describe.py
dotenvmodel/exceptions.py
dotenvmodel/fields.py
dotenvmodel/loading.py
dotenvmodel/logging_config.py
dotenvmodel/py.typed
dotenvmodel/types.py
dotenvmodel/validation.py
dotenvmodel-0.2.0.dist-info/METADATA
dotenvmodel-0.2.0.dist-info/WHEEL
dotenvmodel-0.2.0.dist-info/licenses/LICENSE
dotenvmodel-0.2.0.dist-info/RECORD
