Metadata-Version: 2.4
Name: dotenvmodel
Version: 0.2.0
Summary: Type-safe environment configuration with automatic .env file loading
Project-URL: Homepage, https://github.com/AZX-PBC/dotenvmodel
Project-URL: Repository, https://github.com/AZX-PBC/dotenvmodel
Project-URL: Issues, https://github.com/AZX-PBC/dotenvmodel/issues
Project-URL: Changelog, https://github.com/AZX-PBC/dotenvmodel/blob/main/CHANGELOG.md
Author-email: Rich Evans <re@azx.io>
License: MIT
License-File: LICENSE
Keywords: config,configuration,dotenv,env,environment,settings
Classifier: Development Status :: 3 - Alpha
Classifier: Intended Audience :: Developers
Classifier: License :: OSI Approved :: MIT License
Classifier: Programming Language :: Python :: 3
Classifier: Programming Language :: Python :: 3.12
Classifier: Programming Language :: Python :: 3.13
Classifier: Topic :: Software Development :: Libraries :: Python Modules
Classifier: Topic :: Utilities
Classifier: Typing :: Typed
Requires-Python: >=3.12
Requires-Dist: python-dotenv>=0.19.0
Provides-Extra: dev
Requires-Dist: mypy>=1.0.0; extra == 'dev'
Requires-Dist: pytest-cov>=4.0.0; extra == 'dev'
Requires-Dist: pytest>=7.0.0; extra == 'dev'
Requires-Dist: ruff>=0.1.0; extra == 'dev'
